RD_STT_2/__init__.py
RD_STT_2-2.0.dist-info/METADATA
RD_STT_2-2.0.dist-info/WHEEL
RD_STT_2-2.0.dist-info/top_level.txt
RD_STT_2-2.0.dist-info/RECORD
