Metadata-Version: 2.1
Name: RD_STT_2
Version: 2.0
Summary: this is speech to text package created by Ritik Dwivedi
Author: Ritik Dwivedi
Author-email: example@gmail.com
